sales_analysis/__init__.py
sales_analysis/application/__init__.py
sales_analysis/application/app.py
sales_analysis/application/tests/__init__.py
sales_analysis/application/tests/test_application.py
sales_analysis/data_pipeline/__init__.py
sales_analysis/data_pipeline/_pipeline.py
sales_analysis/data_pipeline/data/commissions.csv
sales_analysis/data_pipeline/data/order_lines.csv
sales_analysis/data_pipeline/data/orders.csv
sales_analysis/data_pipeline/data/product_promotions.csv
sales_analysis/data_pipeline/data/products.csv
sales_analysis/data_pipeline/data/promotions.csv
sales_analysis/data_pipeline/tests/__init__.py
sales_analysis/data_pipeline/tests/test_data.py
sales_analysis-0.4.dist-info/LICENSE.txt
sales_analysis-0.4.dist-info/METADATA
sales_analysis-0.4.dist-info/WHEEL
sales_analysis-0.4.dist-info/desktop.ini
sales_analysis-0.4.dist-info/top_level.txt
sales_analysis-0.4.dist-info/RECORD
