Metadata-Version: 2.1
Name: sales-analysis
Version: 0.4
Summary: A sales analysis package for an imaginary e-shop
Home-page: https://github.com/jbmoorhouse/sales_analysis
Author: Joseph Moorhouse
License: Type license() to see the full license text
Platform: UNKNOWN
Classifier: Programming Language :: Python :: 3.7
Classifier: Operating System :: OS Independent
Requires-Python: >=3.7
Requires-Dist: flask (>=1.1.1)
Requires-Dist: pytest (>=5.2)
Requires-Dist: pandas (>=1.0.0)
Requires-Dist: pytest-flask (>=1.0.0)
